telemod/__init__.py
telemod/listener.py
tele_mod-2.5.dist-info/LICENSE
tele_mod-2.5.dist-info/METADATA
tele_mod-2.5.dist-info/WHEEL
tele_mod-2.5.dist-info/top_level.txt
tele_mod-2.5.dist-info/RECORD
