Metadata-Version: 2.1
Name: tele-mod
Version: 2.5
Summary: Telebot listener
Author: ZAID
Author-email: y8838@hotmail.com
Keywords: python,pytelegrambotapi,telegram,telebot
Classifier: Development Status :: 1 - Planning
Classifier: Intended Audience :: Developers
Classifier: Programming Language :: Python :: 3
Classifier: Operating System :: Unix
Classifier: Operating System :: MacOS :: MacOS X
Classifier: Operating System :: Microsoft :: Windows
Requires-Python: ~=3.6
License-File: LICENSE
Requires-Dist: asyncio
Requires-Dist: pytelegrambotapi
